FreddyApi/__init__.py
FreddyApi/module.py
FreddyApi-1.1.14.dist-info/METADATA
FreddyApi-1.1.14.dist-info/WHEEL
FreddyApi-1.1.14.dist-info/top_level.txt
FreddyApi-1.1.14.dist-info/RECORD
