Metadata-Version: 2.1
Name: FreddyApi
Version: 1.1.14
Summary: A Python package for interacting with the Freddy API
Home-page: https://github.com/Freddy-Development/aitronos-python-package
Author: Phillip Loacker
Author-email: phillip.loacker@aitronos.com
Classifier: Programming Language :: Python :: 3
Classifier: License :: OSI Approved :: MIT License
Classifier: Operating System :: OS Independent
Requires-Python: >=3.6
